[
  {
    "orderNumber": "PVI11030M-",
    "description": "Fronius Symo 10.0-3-M 10kW",
    "imageUrl": "https://image.schrackcdn.com/340x380/f_pvi11030m-.jpg",
    "eshopUrl": "http://www.schrack.sk/eshop/sd/sd?a=PVI11030M-",
    "system": "grid",
    "phase": 3,
    "nominalPower": 10000,
    "maxPower": 15000,
    "minVoltage": 200,
    "ratedVoltage": 600,
    "maxCurrent": 27,
    "mppt": 2,
    "dcInputs": [3, 2]
  },
  {
    "orderNumber": "PVI13030M-",
    "description": "Fronius Symo 3.0-3-M 3kW",
    "imageUrl": "https://image.schrackcdn.com/340x380/f_pvi13030m-.jpg",
    "eshopUrl": "http://www.schrack.sk/eshop/sd/sd?a=PVI13030M-",
    "system": "grid",
    "phase": 3,
    "nominalPower": 3000,
    "maxPower": 6000,
    "minVoltage": 200,
    "ratedVoltage": 595,
    "maxCurrent": 16,
    "mppt": 2,
    "dcInputs": [2, 2]
  },
  {
    "orderNumber": "PVI13730M-",
    "description": "Fronius Symo 3.7-3-M 3,7kW",
    "imageUrl": "https://image.schrackcdn.com/340x380/f_pvi13730m-.jpg",
    "eshopUrl": "http://www.schrack.sk/eshop/sd/sd?a=PVI13730M-",
    "system": "grid",
    "phase": 3,
    "nominalPower": 3700,
    "maxPower": 7400,
    "minVoltage": 200,
    "ratedVoltage": 595,
    "maxCurrent": 16,
    "mppt": 2,
    "dcInputs": [2, 2]
  },
  {
    "orderNumber": "PVI14530M-",
    "description": "Fronius Symo 4.5-3-M 4,5kW",
    "imageUrl": "https://image.schrackcdn.com/340x380/f_pvi14530m-.jpg",
    "eshopUrl": "http://www.schrack.sk/eshop/sd/sd?a=PVI14530M-",
    "system": "grid",
    "phase": 3,
    "nominalPower": 4500,
    "maxPower": 9000,
    "minVoltage": 200,
    "ratedVoltage": 595,
    "maxCurrent": 16,
    "mppt": 2,
    "dcInputs": [2, 2]
  },
  {
    "orderNumber": "PVI15030M-",
    "description": "Fronius Symo 5.0-3-M 5kW",
    "imageUrl": "https://image.schrackcdn.com/340x380/f_pvi15030m-.jpg",
    "eshopUrl": "http://www.schrack.sk/eshop/sd/sd?a=PVI15030M-",
    "system": "grid",
    "phase": 3,
    "nominalPower": 5000,
    "maxPower": 10000,
    "minVoltage": 200,
    "ratedVoltage": 595,
    "maxCurrent": 16,
    "mppt": 2,
    "dcInputs": [2, 2]
  },
  {
    "orderNumber": "PVI16030M-",
    "description": "Fronius Symo 6.0-3-M 6kW",
    "imageUrl": "https://image.schrackcdn.com/340x380/f_pvi16030m-.jpg",
    "eshopUrl": "http://www.schrack.sk/eshop/sd/sd?a=PVI16030M-",
    "system": "grid",
    "phase": 3,
    "nominalPower": 6000,
    "maxPower": 12000,
    "minVoltage": 200,
    "ratedVoltage": 595,
    "maxCurrent": 16,
    "mppt": 2,
    "dcInputs": [2, 2]
  },
  {
    "orderNumber": "PVI17030M-",
    "description": "Fronius Symo 7.0-3-M 7kW",
    "imageUrl": "https://image.schrackcdn.com/340x380/f_pvi17030m-.jpg",
    "eshopUrl": "http://www.schrack.sk/eshop/sd/sd?a=PVI17030M-",
    "system": "grid",
    "phase": 3,
    "nominalPower": 7000,
    "maxPower": 14000,
    "minVoltage": 200,
    "ratedVoltage": 595,
    "maxCurrent": 16,
    "mppt": 2,
    "dcInputs": [2, 2]
  },
  {
    "orderNumber": "PVI18230M-",
    "description": "Fronius Symo 8.2-3-M 8,2kW",
    "imageUrl": "https://image.schrackcdn.com/340x380/f_pvi18230m-.jpg",
    "eshopUrl": "http://www.schrack.sk/eshop/sd/sd?a=PVI18230M-",
    "system": "grid",
    "phase": 3,
    "nominalPower": 8200,
    "maxPower": 16400,
    "minVoltage": 200,
    "ratedVoltage": 595,
    "maxCurrent": 16,
    "mppt": 2,
    "dcInputs": [2, 2]
  },
  {
    "orderNumber": "PVI11030-H",
    "description": "Fronius Symo Gen24 10.0 Plus",
    "imageUrl": "https://image.schrackcdn.com/340x380/f_pvi11030-h.jpg",
    "eshopUrl": "http://www.schrack.sk/eshop/sd/sd?a=PVI11030-H",
    "system": "hybrid, grid",
    "phase": 3,
    "nominalPower": 10000,
    "maxPower": 15000,
    "minVoltage": 80,
    "ratedVoltage": 610,
    "maxCurrent": 25,
    "mppt": 2,
    "dcInputs": [2, 1]
  },
  {
    "orderNumber": "PVI13030-H",
    "description": "Fronius Symo Gen24 3.0 Plus",
    "imageUrl": "https://image.schrackcdn.com/340x380/f_pvi13030-h.jpg",
    "eshopUrl": "http://www.schrack.sk/eshop/sd/sd?a=PVI13030-H",
    "system": "hybrid, grid",
    "phase": 3,
    "nominalPower": 3000,
    "maxPower": 4500,
    "minVoltage": 80,
    "ratedVoltage": 610,
    "maxCurrent": "12,5",
    "mppt": 2,
    "dcInputs": [2, 1]
  },
  {
    "orderNumber": "PVI14030-H",
    "description": "Fronius Symo Gen24 4.0 Plus",
    "imageUrl": "https://image.schrackcdn.com/340x380/f_pvi14030-h.jpg",
    "eshopUrl": "http://www.schrack.sk/eshop/sd/sd?a=PVI14030-H",
    "system": "hybrid, grid",
    "phase": 3,
    "nominalPower": 4000,
    "maxPower": 6000,
    "minVoltage": 80,
    "ratedVoltage": 610,
    "maxCurrent": "12,5",
    "mppt": 2,
    "dcInputs": [2, 1]
  },
  {
    "orderNumber": "PVI15030-H",
    "description": "Fronius Symo Gen24 5.0 Plus",
    "imageUrl": "https://image.schrackcdn.com/340x380/f_pvi15030-h.jpg",
    "eshopUrl": "http://www.schrack.sk/eshop/sd/sd?a=PVI15030-H",
    "system": "hybrid, grid",
    "phase": 3,
    "nominalPower": 5000,
    "maxPower": 7500,
    "minVoltage": 80,
    "ratedVoltage": 610,
    "maxCurrent": "12,5",
    "mppt": 2,
    "dcInputs": [2, 1]
  },
  {
    "orderNumber": "PVI16030-H",
    "description": "Fronius Symo Gen24 6.0 Plus",
    "imageUrl": "https://image.schrackcdn.com/340x380/f_pvi16030-h.jpg",
    "eshopUrl": "http://www.schrack.sk/eshop/sd/sd?a=PVI16030-H",
    "system": "hybrid, grid",
    "phase": 3,
    "nominalPower": 6000,
    "maxPower": 9000,
    "minVoltage": 80,
    "ratedVoltage": 610,
    "maxCurrent": 25,
    "mppt": 2,
    "dcInputs": [2, 1]
  },
  {
    "orderNumber": "PVI18030-H",
    "description": "Fronius Symo Gen24 8.0 Plus",
    "imageUrl": "https://image.schrackcdn.com/340x380/f_pvi18030-h.jpg",
    "eshopUrl": "http://www.schrack.sk/eshop/sd/sd?a=PVI18030-H",
    "system": "hybrid, grid",
    "phase": 3,
    "nominalPower": 8000,
    "maxPower": 12000,
    "minVoltage": 80,
    "ratedVoltage": 610,
    "maxCurrent": 25,
    "mppt": 2,
    "dcInputs": [2, 1]
  },
  {
    "orderNumber": "SUN10KTLM1",
    "description": "Huawei SUN 2000 10KTL M1",
    "imageUrl": "https://www.schrack.at/fileadmin/f/sk/Bilder/Produkte_Loesungen/Produkty/SUN30KTLM1.jpg",
    "eshopUrl": "https://www.schrack.at/fileadmin/f/sk/Bilder/Produkte_Loesungen/Produkty/SUN30KTLM1.pdf",
    "system": "hybrid, grid",
    "phase": 3,
    "nominalPower": 10000,
    "maxPower": 15000,
    "minVoltage": 200,
    "ratedVoltage": 600,
    "maxCurrent": "13,5",
    "mppt": 2,
    "dcInputs": [1, 1]
  },
  {
    "orderNumber": "SUN20KTLL1",
    "description": "Huawei SUN 2000 2KTL L1",
    "imageUrl": "https://www.schrack.at/fileadmin/f/sk/Bilder/Produkte_Loesungen/Produkty/SUN20KTLL1.png",
    "eshopUrl": "https://www.schrack.at/fileadmin/f/sk/Bilder/Produkte_Loesungen/Produkty/SUN20KTLL1.pdf",
    "system": "hybrid, grid",
    "phase": 1,
    "nominalPower": 2000,
    "maxPower": 3000,
    "minVoltage": 100,
    "ratedVoltage": 360,
    "maxCurrent": "12,5",
    "mppt": 2,
    "dcInputs": [1, 1]
  },
  {
    "orderNumber": "SUN36KTLL1",
    "description": "Huawei SUN 2000 3,6KTL L1",
    "imageUrl": "https://www.schrack.at/fileadmin/f/sk/Bilder/Produkte_Loesungen/Produkty/SUN20KTLL1.png",
    "eshopUrl": "https://www.schrack.at/fileadmin/f/sk/Bilder/Produkte_Loesungen/Produkty/SUN20KTLL1.pdf",
    "system": "hybrid, grid",
    "phase": 1,
    "nominalPower": 3600,
    "maxPower": 5520,
    "minVoltage": 100,
    "ratedVoltage": 360,
    "maxCurrent": "12,5",
    "mppt": 2,
    "dcInputs": [1, 1]
  },
  {
    "orderNumber": "SUN30KTLL1",
    "description": "Huawei SUN 2000 3KTL L1",
    "imageUrl": "https://www.schrack.at/fileadmin/f/sk/Bilder/Produkte_Loesungen/Produkty/SUN20KTLL1.png",
    "eshopUrl": "https://www.schrack.at/fileadmin/f/sk/Bilder/Produkte_Loesungen/Produkty/SUN20KTLL1.pdf",
    "system": "hybrid, grid",
    "phase": 1,
    "nominalPower": 3000,
    "maxPower": 4500,
    "minVoltage": 100,
    "ratedVoltage": 360,
    "maxCurrent": "12,5",
    "mppt": 2,
    "dcInputs": [1, 1]
  },
  {
    "orderNumber": "SUN30KTLM1",
    "description": "Huawei SUN 2000 3KTL M1",
    "imageUrl": "https://www.schrack.at/fileadmin/f/sk/Bilder/Produkte_Loesungen/Produkty/SUN30KTLM1.jpg",
    "eshopUrl": "https://www.schrack.at/fileadmin/f/sk/Bilder/Produkte_Loesungen/Produkty/SUN30KTLM1.pdf",
    "system": "hybrid, grid",
    "phase": 3,
    "nominalPower": 3000,
    "maxPower": 4500,
    "minVoltage": 200,
    "ratedVoltage": 600,
    "maxCurrent": "13,5",
    "mppt": 2,
    "dcInputs": [1, 1]
  },
  {
    "orderNumber": "SUN40KTLM1",
    "description": "Huawei SUN 2000 4KTL M1",
    "imageUrl": "https://www.schrack.at/fileadmin/f/sk/Bilder/Produkte_Loesungen/Produkty/SUN30KTLM1.jpg",
    "eshopUrl": "https://www.schrack.at/fileadmin/f/sk/Bilder/Produkte_Loesungen/Produkty/SUN30KTLM1.pdf",
    "system": "hybrid, grid",
    "phase": 3,
    "nominalPower": 4000,
    "maxPower": 6000,
    "minVoltage": 200,
    "ratedVoltage": 600,
    "maxCurrent": "13,5",
    "mppt": 2,
    "dcInputs": [1, 1]
  },
  {
    "orderNumber": "SUN50KTLM1",
    "description": "Huawei SUN 2000 5KTL M1",
    "imageUrl": "https://www.schrack.at/fileadmin/f/sk/Bilder/Produkte_Loesungen/Produkty/SUN30KTLM1.jpg",
    "eshopUrl": "https://www.schrack.at/fileadmin/f/sk/Bilder/Produkte_Loesungen/Produkty/SUN30KTLM1.pdf",
    "system": "hybrid, grid",
    "phase": 3,
    "nominalPower": 5000,
    "maxPower": 7500,
    "minVoltage": 200,
    "ratedVoltage": 600,
    "maxCurrent": "13,5",
    "mppt": 2,
    "dcInputs": [1, 1]
  },
  {
    "orderNumber": "SUN60KTLM1",
    "description": "Huawei SUN 2000 6KTL M1",
    "imageUrl": "https://www.schrack.at/fileadmin/f/sk/Bilder/Produkte_Loesungen/Produkty/SUN30KTLM1.jpg",
    "eshopUrl": "https://www.schrack.at/fileadmin/f/sk/Bilder/Produkte_Loesungen/Produkty/SUN30KTLM1.pdf",
    "system": "hybrid, grid",
    "phase": 3,
    "nominalPower": 6000,
    "maxPower": 9000,
    "minVoltage": 200,
    "ratedVoltage": 600,
    "maxCurrent": "13,5",
    "mppt": 2,
    "dcInputs": [1, 1]
  },
  {
    "orderNumber": "SUN80KTLM1",
    "description": "Huawei SUN 2000 8KTL M1",
    "imageUrl": "https://www.schrack.at/fileadmin/f/sk/Bilder/Produkte_Loesungen/Produkty/SUN30KTLM1.jpg",
    "eshopUrl": "https://www.schrack.at/fileadmin/f/sk/Bilder/Produkte_Loesungen/Produkty/SUN30KTLM1.pdf",
    "system": "hybrid, grid",
    "phase": 3,
    "nominalPower": 8000,
    "maxPower": 12000,
    "minVoltage": 200,
    "ratedVoltage": 600,
    "maxCurrent": "13,5",
    "mppt": 2,
    "dcInputs": [1, 1]
  },
  {
    "orderNumber": "PVI30100--",
    "description": "Kostal Hybrid Plenticore 10",
    "imageUrl": "https://image.schrackcdn.com/340x380/f_pvi30100--.jpg",
    "eshopUrl": "http://www.schrack.sk/eshop/sd/sd?a=PVI30100--",
    "system": "hybrid, grid",
    "phase": 3,
    "nominalPower": 10000,
    "maxPower": 15000,
    "minVoltage": 150,
    "ratedVoltage": 570,
    "maxCurrent": 13,
    "mppt": 3,
    "dcInputs": [1, 1, 1]
  },
  {
    "orderNumber": "PVI30042--",
    "description": "Kostal Hybrid Plenticore 4.2",
    "imageUrl": "https://image.schrackcdn.com/340x380/f_pvi30042--.jpg",
    "eshopUrl": "http://www.schrack.sk/eshop/sd/sd?a=PVI30042--",
    "system": "hybrid, grid",
    "phase": 3,
    "nominalPower": 4200,
    "maxPower": 6300,
    "minVoltage": 150,
    "ratedVoltage": 570,
    "maxCurrent": 13,
    "mppt": 3,
    "dcInputs": [1, 1, 1]
  },
  {
    "orderNumber": "PVI30055--",
    "description": "Kostal Hybrid Plenticore 5.5",
    "imageUrl": "https://image.schrackcdn.com/340x380/f_pvi30055--.jpg",
    "eshopUrl": "http://www.schrack.sk/eshop/sd/sd?a=PVI30055--",
    "system": "hybrid, grid",
    "phase": 3,
    "nominalPower": 5500,
    "maxPower": 8250,
    "minVoltage": 150,
    "ratedVoltage": 570,
    "maxCurrent": 13,
    "mppt": 3,
    "dcInputs": [1, 1, 1]
  },
  {
    "orderNumber": "PVI30070--",
    "description": "Kostal Hybrid Plenticore 7.0",
    "imageUrl": "https://image.schrackcdn.com/340x380/f_pvi30070--.jpg",
    "eshopUrl": "http://www.schrack.sk/eshop/sd/sd?a=PVI30070--",
    "system": "hybrid, grid",
    "phase": 3,
    "nominalPower": 7000,
    "maxPower": 10500,
    "minVoltage": 150,
    "ratedVoltage": 570,
    "maxCurrent": 13,
    "mppt": 3,
    "dcInputs": [1, 1, 1]
  },
  {
    "orderNumber": "PVI30085--",
    "description": "Kostal Hybrid Plenticore 8.5",
    "imageUrl": "https://image.schrackcdn.com/340x380/f_pvi30085--.jpg",
    "eshopUrl": "http://www.schrack.sk/eshop/sd/sd?a=PVI30085--",
    "system": "hybrid, grid",
    "phase": 3,
    "nominalPower": 8500,
    "maxPower": 12750,
    "minVoltage": 150,
    "ratedVoltage": 570,
    "maxCurrent": 13,
    "mppt": 3,
    "dcInputs": [1, 1, 1]
  },
  {
    "orderNumber": "PVI30030--",
    "description": "Kostal Hybrid Plenticore 3.0",
    "imageUrl": "https://image.schrackcdn.com/340x380/f_pvi30030--.jpg",
    "eshopUrl": "http://www.schrack.sk/eshop/sd/sd?a=PVI30030--",
    "system": "hybrid, grid",
    "phase": 3,
    "nominalPower": 3000,
    "maxPower": 4500,
    "minVoltage": 150,
    "ratedVoltage": 570,
    "maxCurrent": 13,
    "mppt": 3,
    "dcInputs": [1, 1, 1]
  }
]
